[
  {
    "date": "2026-04-07",
    "url": "https://www.bloomberg.com/news/live-blog/2026-04-07/iran-latest-trump-hormuz-threats-deadline-middle-east-conflict-oil-markets?srnd=homepage-europe",
    "text": "Israel Warns Iranians as Trump\u2019s Deadline Edges Closer",
    "found_at": "2026-04-07T11:12:22.692201+00:00"
  },
  {
    "date": "2026-04-07",
    "url": "https://www.bloomberg.com/news/live-blog/2026-04-07/iran-latest-trump-hormuz-threats-deadline-middle-east-conflict-oil-markets?srnd=homepage-europe",
    "text": "Vahid Salemi/AP Photo",
    "found_at": "2026-04-07T11:12:22.692201+00:00"
  },
  {
    "date": "2026-04-07",
    "url": "https://www.bloomberg.com/news/live-blog/2026-04-07/iran-latest-trump-hormuz-threats-deadline-middle-east-conflict-oil-markets?srnd=homepage-europe&cursorId=69D4E4AE697C0000",
    "text": "8 minutes agoSome headlines just crossing:\nIsrael Says It Targeted Dozens of Inf",
    "found_at": "2026-04-07T11:12:22.692201+00:00"
  },
  {
    "date": "2026-04-07",
    "url": "https://www.bloomberg.com/news/live-blog/2026-04-07/iran-latest-trump-hormuz-threats-deadline-middle-east-conflict-oil-markets?srnd=homepage-europe&cursorId=69D4DFD54A080000",
    "text": "29 minutes agoKharg Island, a small Iranian outpost in the Persian Gulf, is a cr",
    "found_at": "2026-04-07T11:12:22.692201+00:00"
  },
  {
    "date": "2026-04-07",
    "url": "https://www.bloomberg.com/news/live-blog/2026-04-07/iran-latest-trump-hormuz-threats-deadline-middle-east-conflict-oil-markets?srnd=homepage-europe&cursorId=69D4E6AF697C0000",
    "text": "3 minutes agoBloomberg Economics has looked into the possibilities for what migh",
    "found_at": "2026-04-07T11:15:45.341496+00:00"
  },
  {
    "date": "2026-04-07",
    "url": "https://www.bloomberg.com/news/live-blog/2026-04-07/iran-latest-trump-hormuz-threats-deadline-middle-east-conflict-oil-markets?srnd=homepage-europe&cursorId=69D4F0CA4A080004",
    "text": "2 minutes agoNow also from Fox News on Kharg Island:US Didn\u2019t Intentionally Targ",
    "found_at": "2026-04-07T11:58:18.762187+00:00"
  },
  {
    "date": "2026-04-07",
    "url": "https://www.bloomberg.com/news/live-blog/2026-04-07/iran-latest-trump-hormuz-threats-deadline-middle-east-conflict-oil-markets?srnd=homepage-europe&cursorId=69D4E9FA4A080001",
    "text": "31 minutes agoUS Conducted Strikes on Military Targets on Kharg Island: Axios\nAx",
    "found_at": "2026-04-07T11:58:18.762187+00:00"
  },
  {
    "date": "2026-04-07",
    "url": "https://www.bloomberg.com/news/live-blog/2026-04-07/iran-latest-trump-hormuz-threats-deadline-middle-east-conflict-oil-markets?srnd=homepage-europe&cursorId=69D4F1D849F80040",
    "text": "2 minutes agoFor those of you just joining us, here\u2019s a catchup of the latest de",
    "found_at": "2026-04-07T12:02:43.453893+00:00"
  },
  {
    "date": "2026-04-07",
    "url": "https://www.bloomberg.com/news/live-blog/2026-04-07/iran-latest-trump-hormuz-threats-deadline-middle-east-conflict-oil-markets?srnd=homepage-europe&cursorId=69D4FCEB697C0000",
    "text": "4 minutes agoComing back to Trump\u2019s latest Truth Social post. Those are unpreced",
    "found_at": "2026-04-07T12:51:26.730622+00:00"
  },
  {
    "date": "2026-04-07",
    "url": "https://www.bloomberg.com/news/live-blog/2026-04-07/iran-latest-trump-hormuz-threats-deadline-middle-east-conflict-oil-markets?srnd=homepage-europe&cursorId=69D4F9714A080000",
    "text": "16 minutes agoHere\u2019s our story on those Trump commentsTrump Reiterates Threat to",
    "found_at": "2026-04-07T12:51:26.730622+00:00"
  },
  {
    "date": "2026-04-07",
    "url": "https://www.bloomberg.com/news/live-blog/2026-04-07/iran-latest-trump-hormuz-threats-deadline-middle-east-conflict-oil-markets?srnd=homepage-europe&cursorId=69D4FDC14A080000",
    "text": "2 minutes agoSpeaking in Budapest, US Vice President JD Vance said he\u2019s confiden",
    "found_at": "2026-04-07T12:53:28.631699+00:00"
  },
  {
    "date": "2026-04-07",
    "url": "https://www.bloomberg.com/news/live-blog/2026-04-07/iran-latest-trump-hormuz-threats-deadline-middle-east-conflict-oil-markets?srnd=homepage-europe&cursorId=69D4FF284A080001",
    "text": "5 minutes agoSpeaking in Budapest, US Vice President JD Vance said he\u2019s confiden",
    "found_at": "2026-04-07T13:01:56.059507+00:00"
  },
  {
    "date": "2026-04-07",
    "url": "https://www.bloomberg.com/news/live-blog/2026-04-07/iran-latest-trump-hormuz-threats-deadline-middle-east-conflict-oil-markets?srnd=homepage-europe&cursorId=69D500434A080000",
    "text": "2 minutes agoHere\u2019s some analysis of those Trump comments. Tyler Kendall reports",
    "found_at": "2026-04-07T13:03:41.786820+00:00"
  },
  {
    "date": "2026-04-07",
    "url": "https://www.bloomberg.com/news/live-blog/2026-04-07/iran-latest-trump-hormuz-threats-deadline-middle-east-conflict-oil-markets?srnd=homepage-europe&cursorId=69D502BD49B80077",
    "text": "14 minutes agoQatar has called for restraint as Trump\u2019s deadline for Iran to rea",
    "found_at": "2026-04-07T13:26:48.338495+00:00"
  },
  {
    "date": "2026-04-07",
    "url": "https://www.bloomberg.com/news/live-blog/2026-04-07/iran-latest-trump-hormuz-threats-deadline-middle-east-conflict-oil-markets?srnd=homepage-europe&cursorId=69D50051697C0002",
    "text": "25 minutes agoHere\u2019s some analysis of those Trump comments. Tyler Kendall report",
    "found_at": "2026-04-07T13:26:48.338495+00:00"
  },
  {
    "date": "2026-04-07",
    "url": "https://www.bloomberg.com/news/live-blog/2026-04-07/iran-latest-trump-hormuz-threats-deadline-middle-east-conflict-oil-markets?srnd=homepage-europe&cursorId=69D5088F4A080007",
    "text": "1 minute agoThe UK signaled it won\u2019t let the US use British military bases for s",
    "found_at": "2026-04-07T13:38:40.336131+00:00"
  },
  {
    "date": "2026-04-07",
    "url": "https://www.bloomberg.com/news/live-blog/2026-04-07/iran-latest-trump-hormuz-threats-deadline-middle-east-conflict-oil-markets?srnd=homepage-europe&cursorId=69D50A8149F00001",
    "text": "17 minutes agoFor those of you just joining us, here\u2019s a catchup of the latest d",
    "found_at": "2026-04-07T14:08:08.965767+00:00"
  },
  {
    "date": "2026-04-07",
    "url": "https://www.bloomberg.com/news/live-blog/2026-04-07/iran-latest-trump-hormuz-threats-deadline-middle-east-conflict-oil-markets?srnd=homepage-europe&cursorId=69D50A444A080005",
    "text": "24 minutes agoThe Safeen Prestige, a container ship that was hit in the first we",
    "found_at": "2026-04-07T14:08:08.965767+00:00"
  },
  {
    "date": "2026-04-07",
    "url": "https://www.bloomberg.com/news/live-blog/2026-04-07/iran-latest-trump-hormuz-threats-deadline-middle-east-conflict-oil-markets?srnd=homepage-europe&cursorId=69D5101A4A18000A",
    "text": "4 minutes agoFormer US Representative Marjorie Taylor Greene, who has largely st",
    "found_at": "2026-04-07T14:13:10.469385+00:00"
  },
  {
    "date": "2026-04-07",
    "url": "https://www.bloomberg.com/news/live-blog/2026-04-07/iran-latest-trump-hormuz-threats-deadline-middle-east-conflict-oil-markets?srnd=homepage-europe&cursorId=69D5350349F800EF",
    "text": "22 minutes agoThe idea that Iran is ready for a long war no matter the cost has ",
    "found_at": "2026-04-07T17:08:54.736153+00:00"
  },
  {
    "date": "2026-04-07",
    "url": "https://www.bloomberg.com/news/live-blog/2026-04-07/iran-latest-trump-hormuz-threats-deadline-middle-east-conflict-oil-markets?srnd=homepage-europe&cursorId=69D530F749F80055",
    "text": "39 minutes agoUS Ambassador to the UN Mike Waltz warned at a Security Council me",
    "found_at": "2026-04-07T17:08:54.736153+00:00"
  },
  {
    "date": "2026-04-07",
    "url": "https://www.bloomberg.com/news/live-blog/2026-04-07/iran-latest-trump-hormuz-threats-deadline-middle-east-conflict-oil-markets?srnd=homepage-europe&cursorId=69D53DC049F0013C",
    "text": "7 minutes agoAP is reporting that American journalist Shelly Kittleson, who was ",
    "found_at": "2026-04-07T17:31:35.433601+00:00"
  },
  {
    "date": "2026-04-07",
    "url": "https://www.bloomberg.com/news/live-blog/2026-04-07/iran-latest-trump-hormuz-threats-deadline-middle-east-conflict-oil-markets?srnd=homepage-europe&cursorId=69D53A1A49F0012C",
    "text": "23 minutes agoThe UN Secretary General is worried that \u201can entire people, or an ",
    "found_at": "2026-04-07T17:31:35.433601+00:00"
  },
  {
    "date": "2026-04-07",
    "url": "https://www.bloomberg.com/news/live-blog/2026-04-07/iran-latest-trump-hormuz-threats-deadline-middle-east-conflict-oil-markets?srnd=homepage-europe&cursorId=69D546FC49B8004F",
    "text": "4 minutes agoModerate House Republican Don Bacon of Nebraska, a frequent Trump c",
    "found_at": "2026-04-07T18:07:38.268071+00:00"
  },
  {
    "date": "2026-04-07",
    "url": "https://www.bloomberg.com/news/live-blog/2026-04-07/iran-latest-trump-hormuz-threats-deadline-middle-east-conflict-oil-markets?srnd=homepage-europe&cursorId=69D543A349F00003",
    "text": "15 minutes agoAn Iranian envoy says Tehran will \u201ctake immediate and proportionat",
    "found_at": "2026-04-07T18:07:38.268071+00:00"
  }
]